[
    {
        "timestamp": "2025-08-06T23:24:41.559043",
        "profit_percentage": -0.018655199915749356
    },
    {
        "timestamp": "2025-08-06T23:24:44.539333",
        "profit_percentage": -0.018655199915749356
    },
    {
        "timestamp": "2025-08-06T23:24:47.498762",
        "profit_percentage": -0.018655199915749356
    },
    {
        "timestamp": "2025-08-06T23:24:50.460650",
        "profit_percentage": -0.04376352357222466
    },
    {
        "timestamp": "2025-08-06T23:24:53.411917",
        "profit_percentage": -0.060502406009874866
    },
    {
        "timestamp": "2025-08-06T23:24:56.360086",
        "profit_percentage": -0.04376352357222466
    },
    {
        "timestamp": "2025-08-06T23:24:59.301454",
        "profit_percentage": -0.04376352357222466
    },
    {
        "timestamp": "2025-08-06T23:25:02.247134",
        "profit_percentage": -0.04376352357222466
    },
    {
        "timestamp": "2025-08-06T23:25:05.189574",
        "profit_percentage": -0.04376352357222466
    },
    {
        "timestamp": "2025-08-06T23:25:08.141811",
        "profit_percentage": -0.052132964791049764
    },
    {
        "timestamp": "2025-08-06T23:25:11.119616",
        "profit_percentage": -0.04376352357222466
    },
    {
        "timestamp": "2025-08-06T23:25:14.092166",
        "profit_percentage": -0.04376352357222466
    },
    {
        "timestamp": "2025-08-06T23:25:17.055240",
        "profit_percentage": -0.09825358499499454
    },
    {
        "timestamp": "2025-08-06T23:25:20.009197",
        "profit_percentage": -0.08989220682167343
    },
    {
        "timestamp": "2025-08-06T23:25:22.954801",
        "profit_percentage": -0.08989220682167343
    },
    {
        "timestamp": "2025-08-06T23:25:25.917370",
        "profit_percentage": -0.08989220682167343
    },
    {
        "timestamp": "2025-08-06T23:25:28.864463",
        "profit_percentage": -0.07316945047498277
    },
    {
        "timestamp": "2025-08-06T23:25:31.806141",
        "profit_percentage": -0.07316945047498277
    },
    {
        "timestamp": "2025-08-06T23:25:34.749809",
        "profit_percentage": -0.07316945047498277
    },
    {
        "timestamp": "2025-08-06T23:25:37.700210",
        "profit_percentage": -0.056446694128324405
    },
    {
        "timestamp": "2025-08-06T23:25:40.653162",
        "profit_percentage": -0.08153082864832002
    },
    {
        "timestamp": "2025-08-06T23:25:43.630892",
        "profit_percentage": -0.001916317478099152
    },
    {
        "timestamp": "2025-08-06T23:25:46.623325",
        "profit_percentage": -0.001916317478099152
    },
    {
        "timestamp": "2025-08-06T23:25:49.595047",
        "profit_percentage": -0.056446694128324405
    },
    {
        "timestamp": "2025-08-06T23:25:52.546726",
        "profit_percentage": -0.06480807230166166
    },
    {
        "timestamp": "2025-08-06T23:25:55.495487",
        "profit_percentage": -0.06480807230166166
    },
    {
        "timestamp": "2025-08-06T23:25:58.440081",
        "profit_percentage": -0.018655199915749356
    },
    {
        "timestamp": "2025-08-06T23:26:01.388183",
        "profit_percentage": -0.03539408235339956
    },
    {
        "timestamp": "2025-08-06T23:26:04.336530",
        "profit_percentage": -0.02702464113457446
    },
    {
        "timestamp": "2025-08-06T23:26:07.284256",
        "profit_percentage": -0.02702464113457446
    },
    {
        "timestamp": "2025-08-06T23:26:10.225182",
        "profit_percentage": -0.03539408235339956
    },
    {
        "timestamp": "2025-08-06T23:26:13.170969",
        "profit_percentage": -0.018655199915749356
    },
    {
        "timestamp": "2025-08-06T23:26:16.142958",
        "profit_percentage": -0.010285758696924255
    },
    {
        "timestamp": "2025-08-06T23:26:19.108161",
        "profit_percentage": -0.018655199915749356
    },
    {
        "timestamp": "2025-08-06T23:26:22.065172",
        "profit_percentage": -0.018655199915749356
    },
    {
        "timestamp": "2025-08-06T23:26:25.016608",
        "profit_percentage": -0.018655199915749356
    },
    {
        "timestamp": "2025-08-06T23:26:27.969957",
        "profit_percentage": 0.00645312374072595
    },
    {
        "timestamp": "2025-08-06T23:26:30.929460",
        "profit_percentage": 0.00645312374072595
    },
    {
        "timestamp": "2025-08-06T23:26:33.873774",
        "profit_percentage": -0.001916317478099152
    },
    {
        "timestamp": "2025-08-06T23:26:36.820014",
        "profit_percentage": -0.001916317478099152
    },
    {
        "timestamp": "2025-08-06T23:26:39.796380",
        "profit_percentage": -0.010285758696924255
    },
    {
        "timestamp": "2025-08-06T23:26:42.746592",
        "profit_percentage": -0.010285758696924255
    },
    {
        "timestamp": "2025-08-06T23:26:45.687874",
        "profit_percentage": 0.014822564959551053
    },
    {
        "timestamp": "2025-08-06T23:26:48.665335",
        "profit_percentage": 0.00645312374072595
    },
    {
        "timestamp": "2025-08-06T23:26:51.630638",
        "profit_percentage": 0.00645312374072595
    },
    {
        "timestamp": "2025-08-06T23:26:54.586533",
        "profit_percentage": 0.00645312374072595
    },
    {
        "timestamp": "2025-08-06T23:26:57.542196",
        "profit_percentage": 0.00645312374072595
    },
    {
        "timestamp": "2025-08-06T23:27:00.491459",
        "profit_percentage": 0.00645312374072595
    },
    {
        "timestamp": "2025-08-06T23:27:03.442621",
        "profit_percentage": 0.00645312374072595
    },
    {
        "timestamp": "2025-08-06T23:27:06.381227",
        "profit_percentage": -0.07316945047498277
    },
    {
        "timestamp": "2025-08-06T23:27:09.326555",
        "profit_percentage": -0.07316945047498277
    },
    {
        "timestamp": "2025-08-06T23:27:12.266160",
        "profit_percentage": -0.07316945047498277
    },
    {
        "timestamp": "2025-08-06T23:27:15.215619",
        "profit_percentage": -0.010473381733934094
    },
    {
        "timestamp": "2025-08-06T23:27:18.159466",
        "profit_percentage": -0.018655199915749356
    },
    {
        "timestamp": "2025-08-06T23:27:21.131570",
        "profit_percentage": -0.018655199915749356
    },
    {
        "timestamp": "2025-08-06T23:27:24.088868",
        "profit_percentage": -0.001916317478099152
    },
    {
        "timestamp": "2025-08-06T23:27:27.053293",
        "profit_percentage": -0.001916317478099152
    },
    {
        "timestamp": "2025-08-06T23:27:30.023862",
        "profit_percentage": -0.018655199915749356
    },
    {
        "timestamp": "2025-08-06T23:27:32.971785",
        "profit_percentage": -0.001916317478099152
    },
    {
        "timestamp": "2025-08-06T23:27:35.911865",
        "profit_percentage": -0.001916317478099152
    },
    {
        "timestamp": "2025-08-06T23:27:39.158891",
        "profit_percentage": -0.001916317478099152
    },
    {
        "timestamp": "2025-08-06T23:27:42.100480",
        "profit_percentage": -0.010285758696924255
    },
    {
        "timestamp": "2025-08-06T23:27:45.041489",
        "profit_percentage": -0.010285758696924255
    },
    {
        "timestamp": "2025-08-06T23:27:47.983259",
        "profit_percentage": -0.010285758696924255
    },
    {
        "timestamp": "2025-08-06T23:27:50.962191",
        "profit_percentage": -0.08153082864832002
    },
    {
        "timestamp": "2025-08-06T23:27:53.925220",
        "profit_percentage": -0.018655199915749356
    },
    {
        "timestamp": "2025-08-06T23:27:56.886946",
        "profit_percentage": -0.08042224019686663
    },
    {
        "timestamp": "2025-08-06T23:27:59.836193",
        "profit_percentage": -0.07326654188990679
    },
    {
        "timestamp": "2025-08-06T23:28:02.785879",
        "profit_percentage": -0.05654100277228932
    },
    {
        "timestamp": "2025-08-06T23:28:05.737797",
        "profit_percentage": -0.03981546365468799
    },
    {
        "timestamp": "2025-08-06T23:28:08.683115",
        "profit_percentage": -0.014727154978285998
    },
    {
        "timestamp": "2025-08-06T23:28:11.632394",
        "profit_percentage": -0.03145269409588732
    },
    {
        "timestamp": "2025-08-06T23:28:14.577774",
        "profit_percentage": -0.03981546365468799
    },
    {
        "timestamp": "2025-08-06T23:28:17.546944",
        "profit_percentage": -0.06490377233108999
    },
    {
        "timestamp": "2025-08-06T23:28:20.497997",
        "profit_percentage": -0.08162931144869132
    },
    {
        "timestamp": "2025-08-06T23:28:23.464661",
        "profit_percentage": -0.08162931144869132
    },
    {
        "timestamp": "2025-08-06T23:28:26.440048",
        "profit_percentage": -0.05654100277228932
    },
    {
        "timestamp": "2025-08-06T23:28:29.400184",
        "profit_percentage": -0.05654100277228932
    },
    {
        "timestamp": "2025-08-06T23:28:32.351206",
        "profit_percentage": -0.05654100277228932
    },
    {
        "timestamp": "2025-08-06T23:28:35.309533",
        "profit_percentage": -0.07326654188990679
    },
    {
        "timestamp": "2025-08-06T23:28:38.268897",
        "profit_percentage": -0.07326654188990679
    },
    {
        "timestamp": "2025-08-06T23:28:41.224470",
        "profit_percentage": -0.07326654188990679
    },
    {
        "timestamp": "2025-08-06T23:28:44.185864",
        "profit_percentage": -0.07326654188990679
    },
    {
        "timestamp": "2025-08-06T23:28:47.127381",
        "profit_percentage": -0.07326654188990679
    },
    {
        "timestamp": "2025-08-06T23:28:50.069061",
        "profit_percentage": -0.07326654188990679
    },
    {
        "timestamp": "2025-08-06T23:28:53.012212",
        "profit_percentage": -0.08162931144869132
    },
    {
        "timestamp": "2025-08-06T23:28:56.004863",
        "profit_percentage": -0.08162931144869132
    },
    {
        "timestamp": "2025-08-06T23:28:58.969367",
        "profit_percentage": -0.08999208100749198
    },
    {
        "timestamp": "2025-08-06T23:29:01.932374",
        "profit_percentage": -0.07326654188990679
    },
    {
        "timestamp": "2025-08-06T23:29:04.883399",
        "profit_percentage": -0.08999208100749198
    },
    {
        "timestamp": "2025-08-06T23:29:07.844395",
        "profit_percentage": -0.08999208100749198
    },
    {
        "timestamp": "2025-08-06T23:29:10.794514",
        "profit_percentage": -0.08999208100749198
    },
    {
        "timestamp": "2025-08-06T23:29:13.732990",
        "profit_percentage": -0.08999208100749198
    },
    {
        "timestamp": "2025-08-06T23:29:16.683450",
        "profit_percentage": -0.08999208100749198
    },
    {
        "timestamp": "2025-08-06T23:29:19.635173",
        "profit_percentage": -0.07326654188990679
    },
    {
        "timestamp": "2025-08-06T23:29:22.586932",
        "profit_percentage": -0.09835485056630879
    },
    {
        "timestamp": "2025-08-06T23:29:25.527057",
        "profit_percentage": -0.09835485056630879
    },
    {
        "timestamp": "2025-08-06T23:29:28.521155",
        "profit_percentage": -0.09835485056630879
    },
    {
        "timestamp": "2025-08-06T23:29:31.488624",
        "profit_percentage": -0.09835485056630879
    },
    {
        "timestamp": "2025-08-06T23:29:34.441708",
        "profit_percentage": -0.09835485056630879
    },
    {
        "timestamp": "2025-08-06T23:29:37.391101",
        "profit_percentage": -0.06327287004443152
    },
    {
        "timestamp": "2025-08-06T23:29:40.345796",
        "profit_percentage": -0.06327287004443152
    },
    {
        "timestamp": "2025-08-06T23:29:43.305195",
        "profit_percentage": -0.06327287004443152
    },
    {
        "timestamp": "2025-08-06T23:29:46.243991",
        "profit_percentage": -0.06327287004443152
    },
    {
        "timestamp": "2025-08-06T23:29:49.181406",
        "profit_percentage": -0.05469936667925814
    },
    {
        "timestamp": "2025-08-06T23:29:52.124744",
        "profit_percentage": -0.03793986292586608
    },
    {
        "timestamp": "2025-08-06T23:29:55.071642",
        "profit_percentage": -0.07145887043263406
    },
    {
        "timestamp": "2025-08-06T23:29:58.008760",
        "profit_percentage": -0.09659812606273022
    },
    {
        "timestamp": "2025-08-06T23:30:00.985002",
        "profit_percentage": -0.07145887043263406
    },
    {
        "timestamp": "2025-08-06T23:30:03.992392",
        "profit_percentage": -0.10497787793941817
    },
    {
        "timestamp": "2025-08-06T23:30:06.956958",
        "profit_percentage": -0.10497787793941817
    },
    {
        "timestamp": "2025-08-06T23:30:09.906238",
        "profit_percentage": -0.0630791185559461
    },
    {
        "timestamp": "2025-08-06T23:30:12.849566",
        "profit_percentage": -0.04631961480255404
    },
    {
        "timestamp": "2025-08-06T23:30:15.792008",
        "profit_percentage": -0.042336528685734974
    },
    {
        "timestamp": "2025-08-06T23:30:18.742045",
        "profit_percentage": -0.05071661448984602
    },
    {
        "timestamp": "2025-08-06T23:30:21.699991",
        "profit_percentage": -0.05797411959567581
    },
    {
        "timestamp": "2025-08-06T23:30:24.642788",
        "profit_percentage": -0.06350820712217597
    },
    {
        "timestamp": "2025-08-06T23:30:27.582529",
        "profit_percentage": -0.05576430591874141
    },
    {
        "timestamp": "2025-08-06T23:30:30.528253",
        "profit_percentage": -0.05576430591874141
    },
    {
        "timestamp": "2025-08-06T23:30:33.519942",
        "profit_percentage": -0.04738042573301338
    },
    {
        "timestamp": "2025-08-06T23:30:36.486163",
        "profit_percentage": -0.02222878517581315
    },
    {
        "timestamp": "2025-08-06T23:30:39.444825",
        "profit_percentage": -0.06414818610446944
    },
    {
        "timestamp": "2025-08-06T23:30:42.395435",
        "profit_percentage": -0.07253206629019747
    },
    {
        "timestamp": "2025-08-06T23:30:45.341538",
        "profit_percentage": -0.08929982666165352
    },
    {
        "timestamp": "2025-08-06T23:30:48.285777",
        "profit_percentage": -0.0809159464759255
    },
    {
        "timestamp": "2025-08-06T23:30:51.234956",
        "profit_percentage": -0.026335671411717696
    },
    {
        "timestamp": "2025-08-06T23:30:54.179217",
        "profit_percentage": -0.01794369085864712
    },
    {
        "timestamp": "2025-08-06T23:30:57.117427",
        "profit_percentage": -0.01794369085864712
    },
    {
        "timestamp": "2025-08-06T23:31:00.064175",
        "profit_percentage": -0.03472765196477212
    },
    {
        "timestamp": "2025-08-06T23:31:03.011158",
        "profit_percentage": -0.01794369085864712
    },
    {
        "timestamp": "2025-08-06T23:31:05.985505",
        "profit_percentage": -0.0809159464759255
    },
    {
        "timestamp": "2025-08-06T23:31:09.018053",
        "profit_percentage": -0.07253206629019747
    },
    {
        "timestamp": "2025-08-06T23:31:11.981409",
        "profit_percentage": -0.07253206629019747
    },
    {
        "timestamp": "2025-08-06T23:31:14.932165",
        "profit_percentage": -0.07253206629019747
    },
    {
        "timestamp": "2025-08-06T23:31:17.884905",
        "profit_percentage": -0.06414818610446944
    },
    {
        "timestamp": "2025-08-06T23:31:20.824556",
        "profit_percentage": -0.04738042573301338
    },
    {
        "timestamp": "2025-08-06T23:31:23.764541",
        "profit_percentage": -0.03899654554726921
    },
    {
        "timestamp": "2025-08-06T23:31:26.707718",
        "profit_percentage": -0.03899654554726921
    },
    {
        "timestamp": "2025-08-06T23:31:29.659149",
        "profit_percentage": -0.013844904990085121
    },
    {
        "timestamp": "2025-08-06T23:31:32.600367",
        "profit_percentage": -0.005461024804357092
    },
    {
        "timestamp": "2025-08-06T23:31:35.548446",
        "profit_percentage": -0.005461024804357092
    },
    {
        "timestamp": "2025-08-06T23:31:38.513641",
        "profit_percentage": -0.005461024804357092
    },
    {
        "timestamp": "2025-08-06T23:31:41.503827",
        "profit_percentage": -0.005461024804357092
    },
    {
        "timestamp": "2025-08-06T23:31:44.463365",
        "profit_percentage": -0.005461024804357092
    },
    {
        "timestamp": "2025-08-06T23:31:47.404540",
        "profit_percentage": -0.005461024804357092
    },
    {
        "timestamp": "2025-08-06T23:31:50.363656",
        "profit_percentage": -0.005461024804357092
    },
    {
        "timestamp": "2025-08-06T23:31:53.308957",
        "profit_percentage": -0.0032823063432632893
    },
    {
        "timestamp": "2025-08-06T23:31:56.252230",
        "profit_percentage": -0.032720183338710095
    },
    {
        "timestamp": "2025-08-06T23:31:59.195073",
        "profit_percentage": -0.04109405499364207
    },
    {
        "timestamp": "2025-08-06T23:32:02.137771",
        "profit_percentage": -0.02589161095057206
    },
    {
        "timestamp": "2025-08-06T23:32:05.079130",
        "profit_percentage": -0.009144126506477335
    },
    {
        "timestamp": "2025-08-06T23:32:08.019305",
        "profit_percentage": -0.0007703842844138235
    },
    {
        "timestamp": "2025-08-06T23:32:10.997879",
        "profit_percentage": 0.007603357937633539
    },
    {
        "timestamp": "2025-08-06T23:32:13.959521",
        "profit_percentage": -0.08037740571717415
    },
    {
        "timestamp": "2025-08-06T23:32:16.912649",
        "profit_percentage": -0.07201173068416077
    },
    {
        "timestamp": "2025-08-06T23:32:19.865295",
        "profit_percentage": -0.04066696015109531
    },
    {
        "timestamp": "2025-08-06T23:32:22.815272",
        "profit_percentage": -0.04066696015109531
    },
    {
        "timestamp": "2025-08-06T23:32:25.768371",
        "profit_percentage": -0.04066696015109531
    },
    {
        "timestamp": "2025-08-06T23:32:28.731596",
        "profit_percentage": -0.04066696015109531
    },
    {
        "timestamp": "2025-08-06T23:32:31.675970",
        "profit_percentage": -0.04140474241732502
    },
    {
        "timestamp": "2025-08-06T23:32:34.623063",
        "profit_percentage": -0.04140474241732502
    },
    {
        "timestamp": "2025-08-06T23:32:37.780997",
        "profit_percentage": -0.03303930637602289
    },
    {
        "timestamp": "2025-08-06T23:32:40.725856",
        "profit_percentage": -0.04140474241732502
    },
    {
        "timestamp": "2025-08-06T23:32:43.746839",
        "profit_percentage": -0.04140474241732502
    },
    {
        "timestamp": "2025-08-06T23:32:46.718601",
        "profit_percentage": -0.04140474241732502
    },
    {
        "timestamp": "2025-08-06T23:32:49.684821",
        "profit_percentage": -0.05813561449994544
    },
    {
        "timestamp": "2025-08-06T23:32:52.648577",
        "profit_percentage": -0.012000678414833292
    },
    {
        "timestamp": "2025-08-06T23:32:55.607875",
        "profit_percentage": -0.03731287223254624
    },
    {
        "timestamp": "2025-08-06T23:32:58.580362",
        "profit_percentage": -0.0454946904143615
    },
    {
        "timestamp": "2025-08-06T23:33:01.531874",
        "profit_percentage": -0.0462318297778743
    },
    {
        "timestamp": "2025-08-06T23:33:04.486485",
        "profit_percentage": -0.050410614768252184
    },
    {
        "timestamp": "2025-08-06T23:33:07.456139",
        "profit_percentage": -0.0755362028490096
    },
    {
        "timestamp": "2025-08-06T23:33:10.405673",
        "profit_percentage": -0.058395210497718224
    },
    {
        "timestamp": "2025-08-06T23:33:13.366925",
        "profit_percentage": -0.058395210497718224
    },
    {
        "timestamp": "2025-08-06T23:33:16.365111",
        "profit_percentage": -0.058395210497718224
    },
    {
        "timestamp": "2025-08-06T23:33:19.334528",
        "profit_percentage": -0.058395210497718224
    },
    {
        "timestamp": "2025-08-06T23:33:22.305686",
        "profit_percentage": -0.0628298757155512
    },
    {
        "timestamp": "2025-08-06T23:33:25.260627",
        "profit_percentage": -0.0628298757155512
    },
    {
        "timestamp": "2025-08-06T23:33:28.217320",
        "profit_percentage": -0.07120543472696801
    },
    {
        "timestamp": "2025-08-06T23:33:31.185503",
        "profit_percentage": -0.07958099373840097
    },
    {
        "timestamp": "2025-08-06T23:33:34.141338",
        "profit_percentage": -0.016667286955686998
    },
    {
        "timestamp": "2025-08-06T23:33:37.109600",
        "profit_percentage": -0.016667286955686998
    },
    {
        "timestamp": "2025-08-06T23:33:40.077153",
        "profit_percentage": -0.016667286955686998
    },
    {
        "timestamp": "2025-08-06T23:33:43.041005",
        "profit_percentage": -0.038345367849081734
    },
    {
        "timestamp": "2025-08-06T23:33:46.036712",
        "profit_percentage": -0.01962255154998745
    },
    {
        "timestamp": "2025-08-06T23:33:49.016374",
        "profit_percentage": -0.020719149809474275
    },
    {
        "timestamp": "2025-08-06T23:33:51.990326",
        "profit_percentage": -0.012330218709457406
    },
    {
        "timestamp": "2025-08-06T23:33:54.966995",
        "profit_percentage": -0.020719149809474275
    },
    {
        "timestamp": "2025-08-06T23:33:57.923819",
        "profit_percentage": -0.012330218709457406
    },
    {
        "timestamp": "2025-08-06T23:34:00.874876",
        "profit_percentage": -0.012330218709457406
    },
    {
        "timestamp": "2025-08-06T23:34:03.841818",
        "profit_percentage": -0.012330218709457406
    },
    {
        "timestamp": "2025-08-06T23:34:06.798159",
        "profit_percentage": -0.09198866089074963
    },
    {
        "timestamp": "2025-08-06T23:34:09.752736",
        "profit_percentage": -0.09198866089074963
    },
    {
        "timestamp": "2025-08-06T23:34:12.710288",
        "profit_percentage": -0.08360781940604574
    },
    {
        "timestamp": "2025-08-06T23:34:15.669285",
        "profit_percentage": -0.08360781940604574
    },
    {
        "timestamp": "2025-08-06T23:34:18.675301",
        "profit_percentage": -0.07522697792134184
    },
    {
        "timestamp": "2025-08-06T23:34:21.691492",
        "profit_percentage": -0.07522697792134184
    },
    {
        "timestamp": "2025-08-06T23:34:24.813763",
        "profit_percentage": -0.06684613643665409
    },
    {
        "timestamp": "2025-08-06T23:34:27.778856",
        "profit_percentage": -0.08360781940604574
    },
    {
        "timestamp": "2025-08-06T23:34:30.749976",
        "profit_percentage": -0.07522697792134184
    },
    {
        "timestamp": "2025-08-06T23:34:33.717828",
        "profit_percentage": -0.05008445346724632
    },
    {
        "timestamp": "2025-08-06T23:34:36.668041",
        "profit_percentage": -0.033322770497838536
    },
    {
        "timestamp": "2025-08-06T23:34:39.624712",
        "profit_percentage": -0.024941929013134644
    },
    {
        "timestamp": "2025-08-06T23:34:42.584860",
        "profit_percentage": -0.033322770497838536
    },
    {
        "timestamp": "2025-08-06T23:34:45.540036",
        "profit_percentage": -0.02752602545181433
    },
    {
        "timestamp": "2025-08-06T23:34:48.555222",
        "profit_percentage": -0.02752602545181433
    },
    {
        "timestamp": "2025-08-06T23:34:51.552887",
        "profit_percentage": -0.02752602545181433
    },
    {
        "timestamp": "2025-08-06T23:34:54.529156",
        "profit_percentage": -0.019146103073404547
    },
    {
        "timestamp": "2025-08-06T23:34:57.512075",
        "profit_percentage": -0.044285870208650054
    },
    {
        "timestamp": "2025-08-06T23:35:00.529056",
        "profit_percentage": -0.06104571496548578
    },
    {
        "timestamp": "2025-08-06T23:35:03.487191",
        "profit_percentage": -0.06104571496548578
    },
    {
        "timestamp": "2025-08-06T23:35:06.439254",
        "profit_percentage": -0.03168363172836308
    },
    {
        "timestamp": "2025-08-06T23:35:09.393723",
        "profit_percentage": -0.04007164283495709
    },
    {
        "timestamp": "2025-08-06T23:35:12.350207",
        "profit_percentage": -0.07362368726130084
    },
    {
        "timestamp": "2025-08-06T23:35:15.306057",
        "profit_percentage": -0.07362368726130084
    },
    {
        "timestamp": "2025-08-06T23:35:18.273883",
        "profit_percentage": -0.07362368726130084
    },
    {
        "timestamp": "2025-08-06T23:35:21.231615",
        "profit_percentage": -0.07362368726130084
    },
    {
        "timestamp": "2025-08-06T23:35:24.226358",
        "profit_percentage": -0.05100674654648817
    },
    {
        "timestamp": "2025-08-06T23:35:27.204861",
        "profit_percentage": -0.042619653045312074
    },
    {
        "timestamp": "2025-08-06T23:35:30.176805",
        "profit_percentage": -0.0887365355367981
    },
    {
        "timestamp": "2025-08-06T23:35:33.164924",
        "profit_percentage": -0.08035752987892215
    },
    {
        "timestamp": "2025-08-06T23:35:36.134496",
        "profit_percentage": -0.08035752987892215
    },
    {
        "timestamp": "2025-08-06T23:35:39.388894",
        "profit_percentage": -0.07197852422104618
    },
    {
        "timestamp": "2025-08-06T23:35:42.342397",
        "profit_percentage": -0.06359951856318637
    },
    {
        "timestamp": "2025-08-06T23:35:45.326299",
        "profit_percentage": -0.06359951856318637
    },
    {
        "timestamp": "2025-08-06T23:35:48.287094",
        "profit_percentage": -0.06359951856318637
    },
    {
        "timestamp": "2025-08-06T23:35:51.266955",
        "profit_percentage": -0.06359951856318637
    },
    {
        "timestamp": "2025-08-06T23:35:54.229375",
        "profit_percentage": -0.07479202804231926
    },
    {
        "timestamp": "2025-08-06T23:35:57.226916",
        "profit_percentage": -0.05578129477814351
    },
    {
        "timestamp": "2025-08-06T23:36:00.221561",
        "profit_percentage": -0.08092449445240972
    },
    {
        "timestamp": "2025-08-06T23:36:03.210394",
        "profit_percentage": -0.06416236133623764
    },
    {
        "timestamp": "2025-08-06T23:36:06.174573",
        "profit_percentage": -0.06416236133623764
    },
    {
        "timestamp": "2025-08-06T23:36:09.137520",
        "profit_percentage": -0.06416236133623764
    },
    {
        "timestamp": "2025-08-06T23:36:12.103943",
        "profit_percentage": -0.026423292327073317
    },
    {
        "timestamp": "2025-08-06T23:36:15.071604",
        "profit_percentage": -0.026423292327073317
    },
    {
        "timestamp": "2025-08-06T23:36:18.033911",
        "profit_percentage": -0.026423292327073317
    },
    {
        "timestamp": "2025-08-06T23:36:20.993455",
        "profit_percentage": -0.08514738706180743
    },
    {
        "timestamp": "2025-08-06T23:36:23.984335",
        "profit_percentage": -0.08514738706180743
    },
    {
        "timestamp": "2025-08-06T23:36:27.000921",
        "profit_percentage": -0.07675823067113573
    },
    {
        "timestamp": "2025-08-06T23:36:29.985174",
        "profit_percentage": -0.0683690742804479
    },
    {
        "timestamp": "2025-08-06T23:36:32.955679",
        "profit_percentage": -0.04320160510841669
    },
    {
        "timestamp": "2025-08-06T23:36:35.959574",
        "profit_percentage": -0.05159076149910453
    },
    {
        "timestamp": "2025-08-06T23:36:38.913120",
        "profit_percentage": -0.0683690742804479
    },
    {
        "timestamp": "2025-08-06T23:36:41.880973",
        "profit_percentage": -0.05159076149910453
    },
    {
        "timestamp": "2025-08-06T23:36:44.843171",
        "profit_percentage": -0.05159076149910453
    },
    {
        "timestamp": "2025-08-06T23:36:47.791233",
        "profit_percentage": -0.05159076149910453
    },
    {
        "timestamp": "2025-08-06T23:36:50.745104",
        "profit_percentage": -0.05159076149910453
    },
    {
        "timestamp": "2025-08-06T23:36:53.700415",
        "profit_percentage": -0.05159076149910453
    },
    {
        "timestamp": "2025-08-06T23:36:56.660164",
        "profit_percentage": -0.0435375582930901
    },
    {
        "timestamp": "2025-08-06T23:36:59.650978",
        "profit_percentage": -0.0435375582930901
    },
    {
        "timestamp": "2025-08-06T23:37:02.642924",
        "profit_percentage": -0.05383658153940859
    },
    {
        "timestamp": "2025-08-06T23:37:05.618330",
        "profit_percentage": -0.05383658153940859
    },
    {
        "timestamp": "2025-08-06T23:37:08.581130",
        "profit_percentage": -0.04544620516110275
    },
    {
        "timestamp": "2025-08-06T23:37:11.540829",
        "profit_percentage": -0.04544620516110275
    },
    {
        "timestamp": "2025-08-06T23:37:14.508948",
        "profit_percentage": -0.03705582878278076
    },
    {
        "timestamp": "2025-08-06T23:37:17.467235",
        "profit_percentage": -0.03705582878278076
    },
    {
        "timestamp": "2025-08-06T23:37:20.424707",
        "profit_percentage": -0.04544620516110275
    },
    {
        "timestamp": "2025-08-06T23:37:23.371594",
        "profit_percentage": -0.04544620516110275
    },
    {
        "timestamp": "2025-08-06T23:37:26.333226",
        "profit_percentage": -0.04544620516110275
    },
    {
        "timestamp": "2025-08-06T23:37:29.294187",
        "profit_percentage": -0.04544620516110275
    },
    {
        "timestamp": "2025-08-06T23:37:32.287494",
        "profit_percentage": -0.04544620516110275
    },
    {
        "timestamp": "2025-08-06T23:37:35.278967",
        "profit_percentage": -0.05383658153940859
    },
    {
        "timestamp": "2025-08-06T23:37:38.259680",
        "profit_percentage": -0.05766606381119033
    },
    {
        "timestamp": "2025-08-06T23:37:41.229204",
        "profit_percentage": -0.05766606381119033
    },
    {
        "timestamp": "2025-08-06T23:37:44.202340",
        "profit_percentage": -0.03765737197391029
    },
    {
        "timestamp": "2025-08-06T23:37:47.217638",
        "profit_percentage": -0.029265637367811594
    },
    {
        "timestamp": "2025-08-06T23:37:50.232174",
        "profit_percentage": -0.029265637367811594
    },
    {
        "timestamp": "2025-08-06T23:37:53.372139",
        "profit_percentage": -0.029265637367811594
    },
    {
        "timestamp": "2025-08-06T23:37:56.325302",
        "profit_percentage": -0.029265637367811594
    },
    {
        "timestamp": "2025-08-06T23:37:59.291520",
        "profit_percentage": -0.02087390276169675
    },
    {
        "timestamp": "2025-08-06T23:38:02.247770",
        "profit_percentage": -0.028613786161619196
    },
    {
        "timestamp": "2025-08-06T23:38:05.250584",
        "profit_percentage": -0.037005575485354374
    },
    {
        "timestamp": "2025-08-06T23:38:08.229885",
        "profit_percentage": -0.028613786161619196
    },
    {
        "timestamp": "2025-08-06T23:38:11.220113",
        "profit_percentage": -0.037005575485354374
    },
    {
        "timestamp": "2025-08-06T23:38:14.191466",
        "profit_percentage": -0.06218094345660836
    },
    {
        "timestamp": "2025-08-06T23:38:17.151095",
        "profit_percentage": -0.024421945504229176
    },
    {
        "timestamp": "2025-08-06T23:38:20.109603",
        "profit_percentage": -0.024421945504229176
    },
    {
        "timestamp": "2025-08-06T23:38:23.070375",
        "profit_percentage": -0.04122174016973901
    },
    {
        "timestamp": "2025-08-06T23:38:26.026534",
        "profit_percentage": -0.07482132950077482
    },
    {
        "timestamp": "2025-08-06T23:38:28.972546",
        "profit_percentage": -0.1336206108300915
    },
    {
        "timestamp": "2025-08-06T23:38:31.933769",
        "profit_percentage": -0.07482132950077482
    },
    {
        "timestamp": "2025-08-06T23:38:34.886168",
        "profit_percentage": -0.06642143216801989
    },
    {
        "timestamp": "2025-08-06T23:38:37.868880",
        "profit_percentage": -0.049621637502510064
    },
    {
        "timestamp": "2025-08-06T23:38:40.846829",
        "profit_percentage": -0.058021534835248835
    },
    {
        "timestamp": "2025-08-06T23:38:43.826156",
        "profit_percentage": -0.06832395574505122
    },
    {
        "timestamp": "2025-08-06T23:38:46.793885",
        "profit_percentage": -0.090249217984722
    },
    {
        "timestamp": "2025-08-06T23:38:49.873854",
        "profit_percentage": -0.090249217984722
    },
    {
        "timestamp": "2025-08-06T23:38:53.040469",
        "profit_percentage": -0.08184849900868843
    },
    {
        "timestamp": "2025-08-06T23:38:55.996716",
        "profit_percentage": -0.08184849900868843
    },
    {
        "timestamp": "2025-08-06T23:38:58.943940",
        "profit_percentage": -0.07344778003265486
    },
    {
        "timestamp": "2025-08-06T23:39:01.899082",
        "profit_percentage": -0.07344778003265486
    },
    {
        "timestamp": "2025-08-06T23:39:04.856866",
        "profit_percentage": -0.0986499369607556
    },
    {
        "timestamp": "2025-08-06T23:39:08.338078",
        "profit_percentage": -0.006351478621463065
    },
    {
        "timestamp": "2025-08-06T23:39:11.311661",
        "profit_percentage": -0.0272600746373283
    },
    {
        "timestamp": "2025-08-06T23:39:14.297306",
        "profit_percentage": -0.018851231174853534
    },
    {
        "timestamp": "2025-08-06T23:39:17.260181",
        "profit_percentage": -0.018851231174853534
    },
    {
        "timestamp": "2025-08-06T23:39:20.218219",
        "profit_percentage": -0.01044238771237877
    },
    {
        "timestamp": "2025-08-06T23:39:23.177431",
        "profit_percentage": -0.0272600746373283
    },
    {
        "timestamp": "2025-08-06T23:39:26.137186",
        "profit_percentage": -0.018851231174853534
    },
    {
        "timestamp": "2025-08-06T23:39:29.082213",
        "profit_percentage": -0.0272600746373283
    },
    {
        "timestamp": "2025-08-06T23:39:32.359177",
        "profit_percentage": -0.0272600746373283
    },
    {
        "timestamp": "2025-08-06T23:39:35.308733",
        "profit_percentage": -0.0272600746373283
    },
    {
        "timestamp": "2025-08-06T23:39:38.263348",
        "profit_percentage": -0.07344778003265486
    },
    {
        "timestamp": "2025-08-06T23:39:41.638643",
        "profit_percentage": -0.03566891809980306
    },
    {
        "timestamp": "2025-08-06T23:39:44.590654",
        "profit_percentage": -0.0272600746373283
    },
    {
        "timestamp": "2025-08-06T23:39:47.538081",
        "profit_percentage": -0.018851231174853534
    },
    {
        "timestamp": "2025-08-06T23:39:50.494992",
        "profit_percentage": -0.0272600746373283
    },
    {
        "timestamp": "2025-08-06T23:39:53.453634",
        "profit_percentage": -0.01508057511251079
    },
    {
        "timestamp": "2025-08-06T23:39:56.669261",
        "profit_percentage": -0.01508057511251079
    },
    {
        "timestamp": "2025-08-06T23:39:59.616820",
        "profit_percentage": -0.01508057511251079
    },
    {
        "timestamp": "2025-08-06T23:40:02.568378",
        "profit_percentage": -0.023322274140676186
    },
    {
        "timestamp": "2025-08-06T23:40:05.525777",
        "profit_percentage": -0.08631389855121473
    },
    {
        "timestamp": "2025-08-06T23:40:08.485133",
        "profit_percentage": -0.08631389855121473
    },
    {
        "timestamp": "2025-08-06T23:40:11.456614",
        "profit_percentage": -0.08631389855121473
    },
    {
        "timestamp": "2025-08-06T23:40:14.786522",
        "profit_percentage": -0.08631389855121473
    },
    {
        "timestamp": "2025-08-06T23:40:17.788534",
        "profit_percentage": -0.06111074894184751
    },
    {
        "timestamp": "2025-08-06T23:40:20.752340",
        "profit_percentage": -0.06111074894184751
    },
    {
        "timestamp": "2025-08-06T23:40:23.722221",
        "profit_percentage": -0.06111074894184751
    },
    {
        "timestamp": "2025-08-06T23:40:26.675962",
        "profit_percentage": -0.06111074894184751
    },
    {
        "timestamp": "2025-08-06T23:40:29.643399",
        "profit_percentage": -0.06111074894184751
    },
    {
        "timestamp": "2025-08-06T23:40:32.610859",
        "profit_percentage": -0.07791284868142027
    },
    {
        "timestamp": "2025-08-06T23:40:35.565840",
        "profit_percentage": -0.06951179881162582
    },
    {
        "timestamp": "2025-08-06T23:40:38.838981",
        "profit_percentage": -0.05270969907205305
    },
    {
        "timestamp": "2025-08-06T23:40:41.798112",
        "profit_percentage": -0.03590759933246413
    },
    {
        "timestamp": "2025-08-06T23:40:44.765998",
        "profit_percentage": -0.044308649202242444
    },
    {
        "timestamp": "2025-08-06T23:40:47.757941",
        "profit_percentage": -0.03590759933246413
    },
    {
        "timestamp": "2025-08-06T23:40:50.749596",
        "profit_percentage": -0.03612683102044333
    },
    {
        "timestamp": "2025-08-06T23:40:53.719707",
        "profit_percentage": -0.03590759933246413
    },
    {
        "timestamp": "2025-08-06T23:40:56.694921",
        "profit_percentage": -0.03590759933246413
    },
    {
        "timestamp": "2025-08-06T23:40:59.826561",
        "profit_percentage": -0.04074878904678705
    },
    {
        "timestamp": "2025-08-06T23:41:02.790718",
        "profit_percentage": -0.023947503020900613
    },
    {
        "timestamp": "2025-08-06T23:41:05.746470",
        "profit_percentage": -0.023947503020900613
    },
    {
        "timestamp": "2025-08-06T23:41:08.713027",
        "profit_percentage": -0.023947503020900613
    },
    {
        "timestamp": "2025-08-06T23:41:11.660771",
        "profit_percentage": -0.023947503020900613
    },
    {
        "timestamp": "2025-08-06T23:41:14.619087",
        "profit_percentage": -0.023947503020900613
    },
    {
        "timestamp": "2025-08-06T23:41:17.599758",
        "profit_percentage": -0.023947503020900613
    },
    {
        "timestamp": "2025-08-06T23:41:20.588375",
        "profit_percentage": -0.023947503020900613
    },
    {
        "timestamp": "2025-08-06T23:41:23.556530",
        "profit_percentage": -0.03894865068447021
    },
    {
        "timestamp": "2025-08-06T23:41:26.542460",
        "profit_percentage": -0.030549268166265877
    },
    {
        "timestamp": "2025-08-06T23:41:29.509839",
        "profit_percentage": -0.0221498856480454
    },
    {
        "timestamp": "2025-08-06T23:41:32.473213",
        "profit_percentage": -0.0221498856480454
    },
    {
        "timestamp": "2025-08-06T23:41:35.443863",
        "profit_percentage": -0.04734803320269069
    },
    {
        "timestamp": "2025-08-06T23:41:38.402713",
        "profit_percentage": -0.06414679823913164
    },
    {
        "timestamp": "2025-08-06T23:41:41.356726",
        "profit_percentage": -0.06414679823913164
    },
    {
        "timestamp": "2025-08-06T23:41:44.314733",
        "profit_percentage": -0.06414679823913164
    },
    {
        "timestamp": "2025-08-06T23:41:47.267835",
        "profit_percentage": -0.06414679823913164
    },
    {
        "timestamp": "2025-08-06T23:41:50.264526",
        "profit_percentage": -0.05574741572092731
    },
    {
        "timestamp": "2025-08-06T23:41:53.265070",
        "profit_percentage": -0.05574741572092731
    },
    {
        "timestamp": "2025-08-06T23:41:56.243127",
        "profit_percentage": -0.04734803320269069
    },
    {
        "timestamp": "2025-08-06T23:41:59.208384",
        "profit_percentage": -0.04734803320269069
    },
    {
        "timestamp": "2025-08-06T23:42:02.156343",
        "profit_percentage": -0.04734803320269069
    },
    {
        "timestamp": "2025-08-06T23:42:05.116276",
        "profit_percentage": 0.0030482619066160314
    },
    {
        "timestamp": "2025-08-06T23:42:08.075823",
        "profit_percentage": 0.019847026943040837
    },
    {
        "timestamp": "2025-08-06T23:42:11.091898",
        "profit_percentage": -0.0683059519378304
    },
    {
        "timestamp": "2025-08-06T23:42:14.060612",
        "profit_percentage": -0.0737961015222378
    },
    {
        "timestamp": "2025-08-06T23:42:17.010860",
        "profit_percentage": -0.0737961015222378
    },
    {
        "timestamp": "2025-08-06T23:42:19.958123",
        "profit_percentage": -0.0737961015222378
    },
    {
        "timestamp": "2025-08-06T23:42:23.041347",
        "profit_percentage": -0.0737961015222378
    },
    {
        "timestamp": "2025-08-06T23:42:26.106723",
        "profit_percentage": -0.0737961015222378
    },
    {
        "timestamp": "2025-08-06T23:42:29.086225",
        "profit_percentage": -0.0737961015222378
    },
    {
        "timestamp": "2025-08-06T23:42:32.076183",
        "profit_percentage": -0.0729973215002324
    },
    {
        "timestamp": "2025-08-06T23:42:35.029908",
        "profit_percentage": -0.0729973215002324
    },
    {
        "timestamp": "2025-08-06T23:42:38.065892",
        "profit_percentage": 0.006753941178481362
    },
    {
        "timestamp": "2025-08-06T23:42:41.021775",
        "profit_percentage": -0.010259089633958173
    },
    {
        "timestamp": "2025-08-06T23:42:44.163355",
        "profit_percentage": -0.010042624817672355
    },
    {
        "timestamp": "2025-08-06T23:42:47.116954",
        "profit_percentage": -0.010042624817672355
    },
    {
        "timestamp": "2025-08-06T23:42:50.079399",
        "profit_percentage": -0.010042624817672355
    },
    {
        "timestamp": "2025-08-06T23:42:53.022883",
        "profit_percentage": -0.010042624817672355
    },
    {
        "timestamp": "2025-08-06T23:42:56.047761",
        "profit_percentage": -0.06460714495293084
    },
    {
        "timestamp": "2025-08-06T23:42:59.017033",
        "profit_percentage": -0.04782679185829541
    },
    {
        "timestamp": "2025-08-06T23:43:02.180023",
        "profit_percentage": -0.031046438763659978
    },
    {
        "timestamp": "2025-08-06T23:43:05.152826",
        "profit_percentage": -0.022656262216358414
    },
    {
        "timestamp": "2025-08-06T23:43:08.217634",
        "profit_percentage": -0.04782679185829541
    },
    {
        "timestamp": "2025-08-06T23:43:11.179972",
        "profit_percentage": -0.06835093236028782
    },
    {
        "timestamp": "2025-08-06T23:43:14.133821",
        "profit_percentage": -0.06835093236028782
    },
    {
        "timestamp": "2025-08-06T23:43:17.130943",
        "profit_percentage": -0.0733711628787891
    },
    {
        "timestamp": "2025-08-06T23:43:20.092692",
        "profit_percentage": -0.0733711628787891
    },
    {
        "timestamp": "2025-08-06T23:43:23.086449",
        "profit_percentage": -0.0733711628787891
    },
    {
        "timestamp": "2025-08-06T23:43:26.038305",
        "profit_percentage": -0.05659228136807506
    },
    {
        "timestamp": "2025-08-06T23:43:29.191412",
        "profit_percentage": -0.04820284061270996
    },
    {
        "timestamp": "2025-08-06T23:43:32.169071",
        "profit_percentage": -0.05659228136807506
    },
    {
        "timestamp": "2025-08-06T23:43:35.351592",
        "profit_percentage": -0.05659228136807506
    },
    {
        "timestamp": "2025-08-06T23:43:38.309596",
        "profit_percentage": -0.05659228136807506
    },
    {
        "timestamp": "2025-08-06T23:43:41.269286",
        "profit_percentage": -0.05659228136807506
    },
    {
        "timestamp": "2025-08-06T23:43:44.236145",
        "profit_percentage": -0.064981722123424
    },
    {
        "timestamp": "2025-08-06T23:43:47.192193",
        "profit_percentage": -0.0733711628787891
    },
    {
        "timestamp": "2025-08-06T23:43:50.139386",
        "profit_percentage": -0.0733711628787891
    },
    {
        "timestamp": "2025-08-06T23:43:53.120729",
        "profit_percentage": -0.0733711628787891
    },
    {
        "timestamp": "2025-08-06T23:43:56.067799",
        "profit_percentage": -0.0733711628787891
    },
    {
        "timestamp": "2025-08-06T23:43:59.111099",
        "profit_percentage": -0.0733711628787891
    },
    {
        "timestamp": "2025-08-06T23:44:02.091988",
        "profit_percentage": -0.0020163348889697245
    },
    {
        "timestamp": "2025-08-06T23:44:05.085334",
        "profit_percentage": -0.010413881384187881
    },
    {
        "timestamp": "2025-08-06T23:44:08.055287",
        "profit_percentage": -0.010413881384187881
    },
    {
        "timestamp": "2025-08-06T23:44:11.039315",
        "profit_percentage": -0.0356065208698585
    },
    {
        "timestamp": "2025-08-06T23:44:14.022541",
        "profit_percentage": -0.0356065208698585
    },
    {
        "timestamp": "2025-08-06T23:44:16.974203",
        "profit_percentage": -0.01881142787940604
    },
    {
        "timestamp": "2025-08-06T23:44:19.925930",
        "profit_percentage": -0.060799160355529125
    },
    {
        "timestamp": "2025-08-06T23:44:22.878069",
        "profit_percentage": -0.044004067365076664
    },
    {
        "timestamp": "2025-08-06T23:44:25.850989",
        "profit_percentage": -0.05240161386031097
    },
    {
        "timestamp": "2025-08-06T23:44:28.814756",
        "profit_percentage": -0.044004067365076664
    },
    {
        "timestamp": "2025-08-06T23:44:31.795280",
        "profit_percentage": -0.0356065208698585
    },
    {
        "timestamp": "2025-08-06T23:44:34.819541",
        "profit_percentage": -0.02298583687221558
    },
    {
        "timestamp": "2025-08-06T23:44:37.785099",
        "profit_percentage": -0.02298583687221558
    },
    {
        "timestamp": "2025-08-06T23:44:40.756685",
        "profit_percentage": -0.08599179984118359
    },
    {
        "timestamp": "2025-08-06T23:44:43.713840",
        "profit_percentage": -0.044004067365076664
    },
    {
        "timestamp": "2025-08-06T23:44:46.662911",
        "profit_percentage": -0.060799160355529125
    },
    {
        "timestamp": "2025-08-06T23:44:49.622327",
        "profit_percentage": -0.060799160355529125
    },
    {
        "timestamp": "2025-08-06T23:44:52.564809",
        "profit_percentage": -0.060799160355529125
    },
    {
        "timestamp": "2025-08-06T23:44:55.520172",
        "profit_percentage": -0.060799160355529125
    },
    {
        "timestamp": "2025-08-06T23:44:58.469170",
        "profit_percentage": -0.060799160355529125
    },
    {
        "timestamp": "2025-08-06T23:45:01.420431",
        "profit_percentage": -0.060799160355529125
    },
    {
        "timestamp": "2025-08-06T23:45:04.407058",
        "profit_percentage": -0.060799160355529125
    },
    {
        "timestamp": "2025-08-06T23:45:07.434791",
        "profit_percentage": -0.05240161386031097
    },
    {
        "timestamp": "2025-08-06T23:45:10.431181",
        "profit_percentage": -0.05240161386031097
    },
    {
        "timestamp": "2025-08-06T23:45:13.390799",
        "profit_percentage": -0.06919670685074729
    },
    {
        "timestamp": "2025-08-06T23:45:16.360000",
        "profit_percentage": -0.06919670685074729
    },
    {
        "timestamp": "2025-08-06T23:45:19.320639",
        "profit_percentage": -0.06919670685074729
    },
    {
        "timestamp": "2025-08-06T23:45:22.270094",
        "profit_percentage": -0.060799160355529125
    },
    {
        "timestamp": "2025-08-06T23:45:25.218607",
        "profit_percentage": -0.027208974374640347
    },
    {
        "timestamp": "2025-08-06T23:45:28.179620",
        "profit_percentage": -0.027208974374640347
    },
    {
        "timestamp": "2025-08-06T23:45:31.128759",
        "profit_percentage": -0.010413881384187881
    },
    {
        "timestamp": "2025-08-06T23:45:34.097209",
        "profit_percentage": -0.0020163348889697245
    },
    {
        "timestamp": "2025-08-06T23:45:37.088122",
        "profit_percentage": -0.08176060363415419
    },
    {
        "timestamp": "2025-08-06T23:45:40.066357",
        "profit_percentage": -0.0733711628787891
    },
    {
        "timestamp": "2025-08-06T23:45:43.046206",
        "profit_percentage": -0.010413881384187881
    },
    {
        "timestamp": "2025-08-06T23:45:46.025069",
        "profit_percentage": -0.010413881384187881
    },
    {
        "timestamp": "2025-08-06T23:45:48.982625",
        "profit_percentage": -0.010413881384187881
    },
    {
        "timestamp": "2025-08-06T23:45:51.931880",
        "profit_percentage": -0.010413881384187881
    },
    {
        "timestamp": "2025-08-06T23:45:54.883020",
        "profit_percentage": -0.010413881384187881
    },
    {
        "timestamp": "2025-08-06T23:45:57.837214",
        "profit_percentage": -0.01881142787940604
    },
    {
        "timestamp": "2025-08-06T23:46:00.780956",
        "profit_percentage": -0.07846051725678325
    },
    {
        "timestamp": "2025-08-06T23:46:03.727613",
        "profit_percentage": -0.07007009493058547
    },
    {
        "timestamp": "2025-08-06T23:46:06.679047",
        "profit_percentage": -0.07007009493058547
    },
    {
        "timestamp": "2025-08-06T23:46:09.673153",
        "profit_percentage": -0.07007009493058547
    },
    {
        "timestamp": "2025-08-06T23:46:12.645308",
        "profit_percentage": -0.08685093958298105
    },
    {
        "timestamp": "2025-08-06T23:46:15.620507",
        "profit_percentage": -0.08685093958298105
    },
    {
        "timestamp": "2025-08-06T23:46:18.641005",
        "profit_percentage": -0.08685093958298105
    },
    {
        "timestamp": "2025-08-06T23:46:21.600726",
        "profit_percentage": -0.08685093958298105
    },
    {
        "timestamp": "2025-08-06T23:46:24.556575",
        "profit_percentage": -0.07007009493058547
    },
    {
        "timestamp": "2025-08-06T23:46:27.515074",
        "profit_percentage": -0.07007009493058547
    },
    {
        "timestamp": "2025-08-06T23:46:30.558117",
        "profit_percentage": -0.07007009493058547
    },
    {
        "timestamp": "2025-08-06T23:46:33.520739",
        "profit_percentage": -0.07007009493058547
    },
    {
        "timestamp": "2025-08-06T23:46:36.476831",
        "profit_percentage": -0.07007009493058547
    },
    {
        "timestamp": "2025-08-06T23:46:39.479234",
        "profit_percentage": -0.07007009493058547
    },
    {
        "timestamp": "2025-08-06T23:46:42.468323",
        "profit_percentage": -0.07007009493058547
    },
    {
        "timestamp": "2025-08-06T23:46:45.454849",
        "profit_percentage": -0.07007009493058547
    },
    {
        "timestamp": "2025-08-06T23:46:48.420100",
        "profit_percentage": -0.07007009493058547
    },
    {
        "timestamp": "2025-08-06T23:46:51.409128",
        "profit_percentage": -0.07007009493058547
    },
    {
        "timestamp": "2025-08-06T23:46:54.353998",
        "profit_percentage": -0.053289250278173744
    },
    {
        "timestamp": "2025-08-06T23:46:57.314528",
        "profit_percentage": -0.04489882795197595
    },
    {
        "timestamp": "2025-08-06T23:47:00.263626",
        "profit_percentage": -0.036508405625778166
    },
    {
        "timestamp": "2025-08-06T23:47:03.215391",
        "profit_percentage": -0.019727560973366438
    },
    {
        "timestamp": "2025-08-06T23:47:06.174129",
        "profit_percentage": -0.019727560973366438
    },
    {
        "timestamp": "2025-08-06T23:47:09.136371",
        "profit_percentage": -0.028117983299564223
    },
    {
        "timestamp": "2025-08-06T23:47:12.105370",
        "profit_percentage": -0.036508405625778166
    },
    {
        "timestamp": "2025-08-06T23:47:15.090092",
        "profit_percentage": -0.019727560973366438
    },
    {
        "timestamp": "2025-08-06T23:47:18.066175",
        "profit_percentage": -0.011337138647168647
    },
    {
        "timestamp": "2025-08-06T23:47:21.037168",
        "profit_percentage": -0.011337138647168647
    },
    {
        "timestamp": "2025-08-06T23:47:23.992127",
        "profit_percentage": -0.036508405625778166
    },
    {
        "timestamp": "2025-08-06T23:47:26.952403",
        "profit_percentage": -0.04489882795197595
    },
    {
        "timestamp": "2025-08-06T23:47:29.906164",
        "profit_percentage": -0.07422889635359682
    },
    {
        "timestamp": "2025-08-06T23:47:32.861786",
        "profit_percentage": -0.07422889635359682
    },
    {
        "timestamp": "2025-08-06T23:47:35.819433",
        "profit_percentage": -0.08261122762644003
    },
    {
        "timestamp": "2025-08-06T23:47:38.767958",
        "profit_percentage": -0.07422889635359682
    },
    {
        "timestamp": "2025-08-06T23:47:41.737961",
        "profit_percentage": -0.07815668217190173
    },
    {
        "timestamp": "2025-08-06T23:47:44.711970",
        "profit_percentage": -0.07422889635359682
    },
    {
        "timestamp": "2025-08-06T23:47:47.702779",
        "profit_percentage": -0.07422889635359682
    },
    {
        "timestamp": "2025-08-06T23:47:50.672632",
        "profit_percentage": -0.002946716320954708
    },
    {
        "timestamp": "2025-08-06T23:47:53.635394",
        "profit_percentage": -0.011337138647168647
    },
    {
        "timestamp": "2025-08-06T23:47:56.598491",
        "profit_percentage": -0.028117983299564223
    },
    {
        "timestamp": "2025-08-06T23:47:59.567264",
        "profit_percentage": -0.028117983299564223
    },
    {
        "timestamp": "2025-08-06T23:48:02.553298",
        "profit_percentage": -0.03681780020161214
    },
    {
        "timestamp": "2025-08-06T23:48:05.525164",
        "profit_percentage": -0.03681780020161214
    },
    {
        "timestamp": "2025-08-06T23:48:08.504098",
        "profit_percentage": -0.028426699538480257
    },
    {
        "timestamp": "2025-08-06T23:48:11.455978",
        "profit_percentage": -0.0032533975491168894
    },
    {
        "timestamp": "2025-08-06T23:48:14.410973",
        "profit_percentage": -0.0032533975491168894
    },
    {
        "timestamp": "2025-08-06T23:48:17.396407",
        "profit_percentage": -0.09129926670574662
    },
    {
        "timestamp": "2025-08-06T23:48:20.376015",
        "profit_percentage": -0.10806528461703056
    },
    {
        "timestamp": "2025-08-06T23:48:23.346365",
        "profit_percentage": -0.08291625775012079
    },
    {
        "timestamp": "2025-08-06T23:48:26.320100",
        "profit_percentage": -0.07453324879447883
    },
    {
        "timestamp": "2025-08-06T23:48:29.275014",
        "profit_percentage": -0.066150239838853
    },
    {
        "timestamp": "2025-08-06T23:48:32.241716",
        "profit_percentage": -0.04938422192756905
    },
    {
        "timestamp": "2025-08-06T23:48:35.224092",
        "profit_percentage": -0.04100121297192707
    },
    {
        "timestamp": "2025-08-06T23:48:38.180469",
        "profit_percentage": -0.02518631021954124
    },
    {
        "timestamp": "2025-08-06T23:48:41.134117",
        "profit_percentage": -0.008421857517310566
    },
    {
        "timestamp": "2025-08-06T23:48:44.086085",
        "profit_percentage": -0.008421857517310566
    },
    {
        "timestamp": "2025-08-06T23:48:47.049193",
        "profit_percentage": 0.0007454082886937385
    },
    {
        "timestamp": "2025-08-06T23:48:50.033500",
        "profit_percentage": 0.006275938602923696
    },
    {
        "timestamp": "2025-08-06T23:48:53.023566",
        "profit_percentage": 0.014657289251490175
    },
    {
        "timestamp": "2025-08-06T23:48:55.997213",
        "profit_percentage": -0.0038784012463175736
    },
    {
        "timestamp": "2025-08-06T23:48:58.973889",
        "profit_percentage": -0.012259603291314198
    },
    {
        "timestamp": "2025-08-06T23:49:01.940035",
        "profit_percentage": -0.029022007381291296
    },
    {
        "timestamp": "2025-08-06T23:49:04.898897",
        "profit_percentage": -0.04578441147125225
    },
    {
        "timestamp": "2025-08-06T23:49:07.848423",
        "profit_percentage": -0.05416561351624887
    },
    {
        "timestamp": "2025-08-06T23:49:10.898229",
        "profit_percentage": 0.004502800798662902
    },
    {
        "timestamp": "2025-08-06T23:49:13.844765",
        "profit_percentage": -0.033228757155321566
    },
    {
        "timestamp": "2025-08-06T23:49:16.797861",
        "profit_percentage": -0.024855629486094957
    },
    {
        "timestamp": "2025-08-06T23:49:19.750738",
        "profit_percentage": -0.024855629486094957
    },
    {
        "timestamp": "2025-08-06T23:49:22.815473",
        "profit_percentage": -0.024855629486094957
    },
    {
        "timestamp": "2025-08-06T23:49:25.787793",
        "profit_percentage": 0.00026375352158486913
    },
    {
        "timestamp": "2025-08-06T23:49:28.746691",
        "profit_percentage": 0.00026375352158486913
    },
    {
        "timestamp": "2025-08-06T23:49:31.710879",
        "profit_percentage": -0.07925275341991975
    },
    {
        "timestamp": "2025-08-06T23:49:34.668691",
        "profit_percentage": -0.07925275341991975
    },
    {
        "timestamp": "2025-08-06T23:49:37.645738",
        "profit_percentage": -0.07925275341991975
    },
    {
        "timestamp": "2025-08-06T23:49:40.591656",
        "profit_percentage": -0.07088768458388986
    },
    {
        "timestamp": "2025-08-06T23:49:43.544094",
        "profit_percentage": -0.07925275341991975
    },
    {
        "timestamp": "2025-08-06T23:49:46.492219",
        "profit_percentage": -0.07925275341991975
    },
    {
        "timestamp": "2025-08-06T23:49:49.445064",
        "profit_percentage": -0.08761782225598193
    },
    {
        "timestamp": "2025-08-06T23:49:52.394558",
        "profit_percentage": -0.08761782225598193
    },
    {
        "timestamp": "2025-08-06T23:49:55.425143",
        "profit_percentage": 0.008636881190795328
    },
    {
        "timestamp": "2025-08-06T23:49:58.391497",
        "profit_percentage": -0.00810937414764174
    },
    {
        "timestamp": "2025-08-06T23:50:01.352547",
        "profit_percentage": -0.00810937414764174
    },
    {
        "timestamp": "2025-08-06T23:50:04.324876",
        "profit_percentage": -0.024855629486094957
    },
    {
        "timestamp": "2025-08-06T23:50:07.280295",
        "profit_percentage": -0.024855629486094957
    },
    {
        "timestamp": "2025-08-06T23:50:10.258080",
        "profit_percentage": -0.03286638038866711
    },
    {
        "timestamp": "2025-08-06T23:50:13.206230",
        "profit_percentage": -0.03286638038866711
    },
    {
        "timestamp": "2025-08-06T23:50:16.152402",
        "profit_percentage": -0.03286638038866711
    },
    {
        "timestamp": "2025-08-06T23:50:19.103917",
        "profit_percentage": -0.03286638038866711
    },
    {
        "timestamp": "2025-08-06T23:50:22.068710",
        "profit_percentage": -0.03286638038866711
    },
    {
        "timestamp": "2025-08-06T23:50:25.019124",
        "profit_percentage": -0.0412388371407214
    },
    {
        "timestamp": "2025-08-06T23:50:28.003759",
        "profit_percentage": -0.02449392363661283
    },
    {
        "timestamp": "2025-08-06T23:50:30.977897",
        "profit_percentage": -0.02449392363661283
    },
    {
        "timestamp": "2025-08-06T23:50:33.963420",
        "profit_percentage": -0.04980193246303086
    },
    {
        "timestamp": "2025-08-06T23:50:36.923116",
        "profit_percentage": -0.049611293892791834
    },
    {
        "timestamp": "2025-08-06T23:50:39.884269",
        "profit_percentage": -0.049611293892791834
    },
    {
        "timestamp": "2025-08-06T23:50:42.836406",
        "profit_percentage": -0.049611293892791834
    },
    {
        "timestamp": "2025-08-06T23:50:45.790293",
        "profit_percentage": -0.06635620739691654
    },
    {
        "timestamp": "2025-08-06T23:50:48.749293",
        "profit_percentage": -0.03286638038866711
    },
    {
        "timestamp": "2025-08-06T23:50:51.704264",
        "profit_percentage": -0.02449392363661283
    },
    {
        "timestamp": "2025-08-06T23:50:54.901522",
        "profit_percentage": 0.0006234466195823271
    },
    {
        "timestamp": "2025-08-06T23:50:57.852570",
        "profit_percentage": -0.0028577500590739905
    },
    {
        "timestamp": "2025-08-06T23:51:00.927587",
        "profit_percentage": -0.0028577500590739905
    },
    {
        "timestamp": "2025-08-06T23:51:03.901191",
        "profit_percentage": -0.01295373409673834
    },
    {
        "timestamp": "2025-08-06T23:51:06.927688",
        "profit_percentage": -0.01295373409673834
    },
    {
        "timestamp": "2025-08-06T23:51:09.898644",
        "profit_percentage": -0.01295373409673834
    },
    {
        "timestamp": "2025-08-06T23:51:12.860880",
        "profit_percentage": -0.01295373409673834
    },
    {
        "timestamp": "2025-08-06T23:51:15.907265",
        "profit_percentage": -0.01295373409673834
    },
    {
        "timestamp": "2025-08-06T23:51:18.872760",
        "profit_percentage": -0.01295373409673834
    },
    {
        "timestamp": "2025-08-06T23:51:21.819779",
        "profit_percentage": -0.01295373409673834
    },
    {
        "timestamp": "2025-08-06T23:51:24.787177",
        "profit_percentage": -0.01295373409673834
    },
    {
        "timestamp": "2025-08-06T23:51:27.743083",
        "profit_percentage": -0.02132435329021056
    },
    {
        "timestamp": "2025-08-06T23:51:30.728795",
        "profit_percentage": -0.02132435329021056
    },
    {
        "timestamp": "2025-08-06T23:51:33.704359",
        "profit_percentage": -0.01295373409673834
    },
    {
        "timestamp": "2025-08-06T23:51:36.671694",
        "profit_percentage": -0.01295373409673834
    },
    {
        "timestamp": "2025-08-06T23:51:39.633573",
        "profit_percentage": -0.029694972483666635
    },
    {
        "timestamp": "2025-08-06T23:51:42.624298",
        "profit_percentage": -0.02132435329021056
    },
    {
        "timestamp": "2025-08-06T23:51:45.598407",
        "profit_percentage": -0.054806830064050994
    },
    {
        "timestamp": "2025-08-06T23:51:48.556661",
        "profit_percentage": -0.054806830064050994
    },
    {
        "timestamp": "2025-08-06T23:51:51.501387",
        "profit_percentage": -0.055075354333586096
    },
    {
        "timestamp": "2025-08-06T23:51:54.446855",
        "profit_percentage": -0.055075354333586096
    },
    {
        "timestamp": "2025-08-06T23:51:57.397787",
        "profit_percentage": -0.055075354333586096
    },
    {
        "timestamp": "2025-08-06T23:52:00.362376",
        "profit_percentage": -0.055075354333586096
    },
    {
        "timestamp": "2025-08-06T23:52:03.356017",
        "profit_percentage": -0.055075354333586096
    },
    {
        "timestamp": "2025-08-06T23:52:06.332106",
        "profit_percentage": -0.04670405651586213
    },
    {
        "timestamp": "2025-08-06T23:52:09.306945",
        "profit_percentage": -0.04670405651586213
    },
    {
        "timestamp": "2025-08-06T23:52:12.285524",
        "profit_percentage": -0.04670405651586213
    },
    {
        "timestamp": "2025-08-06T23:52:15.245070",
        "profit_percentage": -0.04670405651586213
    },
    {
        "timestamp": "2025-08-06T23:52:18.199614",
        "profit_percentage": -0.04670405651586213
    },
    {
        "timestamp": "2025-08-06T23:52:21.145647",
        "profit_percentage": -0.004847567427306904
    },
    {
        "timestamp": "2025-08-06T23:52:24.121713",
        "profit_percentage": -0.004847567427306904
    },
    {
        "timestamp": "2025-08-06T23:52:28.692299",
        "profit_percentage": -0.004847567427306904
    },
    {
        "timestamp": "2025-08-06T23:52:33.997574",
        "profit_percentage": -0.0509098481047329
    },
    {
        "timestamp": "2025-08-06T23:52:40.850586",
        "profit_percentage": -0.0509098481047329
    },
    {
        "timestamp": "2025-08-06T23:52:48.099829",
        "profit_percentage": -0.0592730888504372
    },
    {
        "timestamp": "2025-08-06T23:52:55.673783",
        "profit_percentage": -0.0592730888504372
    },
    {
        "timestamp": "2025-08-06T23:52:58.638734",
        "profit_percentage": -0.0509098481047329
    },
    {
        "timestamp": "2025-08-06T23:53:01.612448",
        "profit_percentage": 0.02026632602583269
    },
    {
        "timestamp": "2025-08-06T23:53:04.669743",
        "profit_percentage": -0.0299614608804465
    },
    {
        "timestamp": "2025-08-06T23:53:07.662471",
        "profit_percentage": -0.0299614608804465
    },
    {
        "timestamp": "2025-08-06T23:53:10.709471",
        "profit_percentage": -0.0299614608804465
    },
    {
        "timestamp": "2025-08-06T23:53:13.680121",
        "profit_percentage": -0.0299614608804465
    },
    {
        "timestamp": "2025-08-06T23:53:16.646729",
        "profit_percentage": -0.0005933013232060282
    },
    {
        "timestamp": "2025-08-06T23:53:19.614242",
        "profit_percentage": -0.01735204218104126
    },
    {
        "timestamp": "2025-08-06T23:53:22.577907",
        "profit_percentage": -0.01735204218104126
    },
    {
        "timestamp": "2025-08-06T23:53:25.550068",
        "profit_percentage": -0.025731412609950804
    },
    {
        "timestamp": "2025-08-06T23:53:28.514282",
        "profit_percentage": -0.03411078303887649
    },
    {
        "timestamp": "2025-08-06T23:53:31.575651",
        "profit_percentage": -0.03411078303887649
    },
    {
        "timestamp": "2025-08-06T23:53:34.538569",
        "profit_percentage": -0.03411078303887649
    },
    {
        "timestamp": "2025-08-06T23:53:37.488870",
        "profit_percentage": -0.025731412609950804
    },
    {
        "timestamp": "2025-08-06T23:53:40.875499",
        "profit_percentage": -0.01735204218104126
    },
    {
        "timestamp": "2025-08-06T23:53:43.935557",
        "profit_percentage": -0.05086952389669557
    },
    {
        "timestamp": "2025-08-06T23:53:47.034825",
        "profit_percentage": -0.05086952389669557
    },
    {
        "timestamp": "2025-08-06T23:53:49.989230",
        "profit_percentage": -0.05086952389669557
    },
    {
        "timestamp": "2025-08-06T23:53:52.973830",
        "profit_percentage": -0.05086952389669557
    },
    {
        "timestamp": "2025-08-06T23:53:55.936758",
        "profit_percentage": -0.05086952389669557
    },
    {
        "timestamp": "2025-08-06T23:53:58.906089",
        "profit_percentage": -0.05086952389669557
    },
    {
        "timestamp": "2025-08-06T23:54:01.860967",
        "profit_percentage": -0.05635813418323401
    },
    {
        "timestamp": "2025-08-06T23:54:04.800038",
        "profit_percentage": -0.047979223899377844
    },
    {
        "timestamp": "2025-08-06T23:54:07.751405",
        "profit_percentage": -0.06734196806748634
    },
    {
        "timestamp": "2025-08-06T23:54:10.703766",
        "profit_percentage": -0.06734196806748634
    },
    {
        "timestamp": "2025-08-06T23:54:13.932493",
        "profit_percentage": -0.06734196806748634
    },
    {
        "timestamp": "2025-08-06T23:54:17.604821",
        "profit_percentage": -0.06734196806748634
    },
    {
        "timestamp": "2025-08-06T23:54:20.559462",
        "profit_percentage": -0.06734196806748634
    },
    {
        "timestamp": "2025-08-06T23:54:23.664036",
        "profit_percentage": -0.07431381206397121
    },
    {
        "timestamp": "2025-08-06T23:54:26.652172",
        "profit_percentage": -0.07431381206397121
    },
    {
        "timestamp": "2025-08-06T23:54:29.604377",
        "profit_percentage": -0.07431381206397121
    },
    {
        "timestamp": "2025-08-06T23:54:32.552846",
        "profit_percentage": -0.07431381206397121
    },
    {
        "timestamp": "2025-08-06T23:54:35.502344",
        "profit_percentage": -0.07431381206397121
    },
    {
        "timestamp": "2025-08-06T23:54:38.462970",
        "profit_percentage": -0.07431381206397121
    },
    {
        "timestamp": "2025-08-06T23:54:41.744238",
        "profit_percentage": -0.07431381206397121
    },
    {
        "timestamp": "2025-08-06T23:54:44.720940",
        "profit_percentage": -0.07431381206397121
    },
    {
        "timestamp": "2025-08-06T23:54:47.701838",
        "profit_percentage": -0.07431381206397121
    },
    {
        "timestamp": "2025-08-06T23:54:50.675916",
        "profit_percentage": -0.024045168052259796
    },
    {
        "timestamp": "2025-08-06T23:54:53.631369",
        "profit_percentage": -0.015667060716963797
    },
    {
        "timestamp": "2025-08-06T23:54:56.591304",
        "profit_percentage": -0.015667060716963797
    },
    {
        "timestamp": "2025-08-06T23:54:59.541804",
        "profit_percentage": -0.015667060716963797
    },
    {
        "timestamp": "2025-08-06T23:55:02.497271",
        "profit_percentage": -0.015667060716963797
    },
    {
        "timestamp": "2025-08-06T23:55:05.451386",
        "profit_percentage": -0.017947218351773004
    },
    {
        "timestamp": "2025-08-06T23:55:08.404559",
        "profit_percentage": -0.017947218351773004
    },
    {
        "timestamp": "2025-08-06T23:55:11.351117",
        "profit_percentage": -0.017947218351773004
    },
    {
        "timestamp": "2025-08-06T23:55:14.315299",
        "profit_percentage": -0.0011899816499133015
    },
    {
        "timestamp": "2025-08-06T23:55:17.328777",
        "profit_percentage": -0.0011899816499133015
    },
    {
        "timestamp": "2025-08-06T23:55:20.607489",
        "profit_percentage": -0.06404576305521138
    },
    {
        "timestamp": "2025-08-06T23:55:23.579377",
        "profit_percentage": -0.06404576305521138
    },
    {
        "timestamp": "2025-08-06T23:55:26.546234",
        "profit_percentage": -0.07241630951948318
    },
    {
        "timestamp": "2025-08-06T23:55:29.511753",
        "profit_percentage": -0.06404576305521138
    },
    {
        "timestamp": "2025-08-06T23:55:32.462578",
        "profit_percentage": -0.08915740244802674
    },
    {
        "timestamp": "2025-08-06T23:55:35.571266",
        "profit_percentage": -0.08200384461746908
    },
    {
        "timestamp": "2025-08-06T23:55:38.531164",
        "profit_percentage": 0.005969874596477677
    },
    {
        "timestamp": "2025-08-06T23:55:41.487908",
        "profit_percentage": -0.0024093436586108455
    },
    {
        "timestamp": "2025-08-06T23:55:44.432812",
        "profit_percentage": -0.07363269882696825
    },
    {
        "timestamp": "2025-08-06T23:55:47.411230",
        "profit_percentage": -0.07363269882696825
    },
    {
        "timestamp": "2025-08-06T23:55:50.433829",
        "profit_percentage": -0.07363269882696825
    },
    {
        "timestamp": "2025-08-06T23:55:53.412406",
        "profit_percentage": -0.05689040724598274
    },
    {
        "timestamp": "2025-08-06T23:55:56.379573",
        "profit_percentage": -0.040148115664981075
    },
    {
        "timestamp": "2025-08-06T23:55:59.340609",
        "profit_percentage": -0.040148115664981075
    },
    {
        "timestamp": "2025-08-06T23:56:02.339775",
        "profit_percentage": -0.040148115664981075
    },
    {
        "timestamp": "2025-08-06T23:56:05.296650",
        "profit_percentage": -0.040148115664981075
    },
    {
        "timestamp": "2025-08-06T23:56:08.311973",
        "profit_percentage": -0.040148115664981075
    },
    {
        "timestamp": "2025-08-06T23:56:11.265992",
        "profit_percentage": -0.06526155303648358
    },
    {
        "timestamp": "2025-08-06T23:56:14.239601",
        "profit_percentage": -0.06526155303648358
    },
    {
        "timestamp": "2025-08-06T23:56:17.189874",
        "profit_percentage": -0.06526155303648358
    },
    {
        "timestamp": "2025-08-06T23:56:20.165690",
        "profit_percentage": -0.010788561913715517
    },
    {
        "timestamp": "2025-08-06T23:56:23.179276",
        "profit_percentage": -0.09037499040796991
    },
    {
        "timestamp": "2025-08-06T23:56:26.158208",
        "profit_percentage": -0.0024093436586108455
    },
    {
        "timestamp": "2025-08-06T23:56:29.141958",
        "profit_percentage": -0.0024093436586108455
    },
    {
        "timestamp": "2025-08-06T23:56:32.124894",
        "profit_percentage": -0.027546998423908713
    },
    {
        "timestamp": "2025-08-06T23:56:35.078485",
        "profit_percentage": -0.03592621667901338
    },
    {
        "timestamp": "2025-08-06T23:56:38.033240",
        "profit_percentage": -0.03592621667901338
    },
    {
        "timestamp": "2025-08-06T23:56:40.994855",
        "profit_percentage": -0.03592621667901338
    },
    {
        "timestamp": "2025-08-06T23:56:43.955454",
        "profit_percentage": -0.03592621667901338
    },
    {
        "timestamp": "2025-08-06T23:56:46.918945",
        "profit_percentage": -0.03592621667901338
    },
    {
        "timestamp": "2025-08-06T23:56:49.871977",
        "profit_percentage": -0.03592621667901338
    },
    {
        "timestamp": "2025-08-06T23:56:52.837727",
        "profit_percentage": -0.06944308969939976
    },
    {
        "timestamp": "2025-08-06T23:56:55.841682",
        "profit_percentage": -0.06944308969939976
    },
    {
        "timestamp": "2025-08-06T23:56:58.824981",
        "profit_percentage": -0.044305434934101905
    },
    {
        "timestamp": "2025-08-06T23:57:01.791826",
        "profit_percentage": -0.027546998423908713
    },
    {
        "timestamp": "2025-08-06T23:57:04.764900",
        "profit_percentage": -0.010788561913715517
    },
    {
        "timestamp": "2025-08-06T23:57:07.719600",
        "profit_percentage": -0.0024093436586108455
    },
    {
        "timestamp": "2025-08-06T23:57:10.685320",
        "profit_percentage": -0.09037499040796991
    },
    {
        "timestamp": "2025-08-06T23:57:13.649988",
        "profit_percentage": -0.061063871444311246
    },
    {
        "timestamp": "2025-08-06T23:57:16.605848",
        "profit_percentage": -0.06944308969939976
    },
    {
        "timestamp": "2025-08-06T23:57:19.567754",
        "profit_percentage": -0.044305434934101905
    },
    {
        "timestamp": "2025-08-06T23:57:22.520092",
        "profit_percentage": -0.027546998423908713
    },
    {
        "timestamp": "2025-08-06T23:57:25.492326",
        "profit_percentage": -0.027546998423908713
    },
    {
        "timestamp": "2025-08-06T23:57:28.483389",
        "profit_percentage": -0.0024093436586108455
    },
    {
        "timestamp": "2025-08-06T23:57:31.465787",
        "profit_percentage": -0.09874613619847074
    },
    {
        "timestamp": "2025-08-06T23:57:34.432732",
        "profit_percentage": -0.05689040724598274
    },
    {
        "timestamp": "2025-08-06T23:57:37.394504",
        "profit_percentage": -0.0024093436586108455
    },
    {
        "timestamp": "2025-08-06T23:57:40.352885",
        "profit_percentage": -0.019167780168820186
    },
    {
        "timestamp": "2025-08-06T23:57:43.323878",
        "profit_percentage": -0.027546998423908713
    },
    {
        "timestamp": "2025-08-06T23:57:46.279041",
        "profit_percentage": -0.019167780168820186
    },
    {
        "timestamp": "2025-08-06T23:57:49.234944",
        "profit_percentage": -0.09037499040796991
    },
    {
        "timestamp": "2025-08-06T23:57:52.191302",
        "profit_percentage": -0.09037499040796991
    },
    {
        "timestamp": "2025-08-06T23:57:55.146049",
        "profit_percentage": 0.005969874596477677
    },
    {
        "timestamp": "2025-08-06T23:57:58.142958",
        "profit_percentage": -0.0024093436586108455
    },
    {
        "timestamp": "2025-08-06T23:58:01.116939",
        "profit_percentage": -0.09037499040796991
    },
    {
        "timestamp": "2025-08-06T23:58:04.088735",
        "profit_percentage": -0.08200384461746908
    },
    {
        "timestamp": "2025-08-06T23:58:07.052719",
        "profit_percentage": -0.07239894484598608
    },
    {
        "timestamp": "2025-08-06T23:58:10.015702",
        "profit_percentage": -0.07239894484598608
    },
    {
        "timestamp": "2025-08-06T23:58:13.053128",
        "profit_percentage": -0.06402839692713642
    },
    {
        "timestamp": "2025-08-06T23:58:16.006918",
        "profit_percentage": -0.07239894484598608
    },
    {
        "timestamp": "2025-08-06T23:58:18.952221",
        "profit_percentage": -0.07239894484598608
    },
    {
        "timestamp": "2025-08-06T23:58:21.903988",
        "profit_percentage": -0.07239894484598608
    },
    {
        "timestamp": "2025-08-06T23:58:24.852082",
        "profit_percentage": -0.07239894484598608
    },
    {
        "timestamp": "2025-08-06T23:58:27.800520",
        "profit_percentage": -0.08076949276481958
    },
    {
        "timestamp": "2025-08-06T23:58:30.803604",
        "profit_percentage": -0.08076949276481958
    },
    {
        "timestamp": "2025-08-06T23:58:33.784401",
        "profit_percentage": -0.10588113652135239
    },
    {
        "timestamp": "2025-08-06T23:58:36.769263",
        "profit_percentage": -0.11425168444020205
    },
    {
        "timestamp": "2025-08-06T23:58:39.737979",
        "profit_percentage": -0.06402839692713642
    },
    {
        "timestamp": "2025-08-06T23:58:42.696755",
        "profit_percentage": -0.04728730108945327
    },
    {
        "timestamp": "2025-08-06T23:58:45.692577",
        "profit_percentage": -0.030546205251753958
    },
    {
        "timestamp": "2025-08-06T23:58:48.642538",
        "profit_percentage": -0.030546205251753958
    },
    {
        "timestamp": "2025-08-06T23:58:51.602082",
        "profit_percentage": -0.05565784900828677
    },
    {
        "timestamp": "2025-08-06T23:58:54.673000",
        "profit_percentage": -0.05565784900828677
    },
    {
        "timestamp": "2025-08-06T23:58:57.621709",
        "profit_percentage": -0.05565784900828677
    },
    {
        "timestamp": "2025-08-06T23:59:00.593009",
        "profit_percentage": -0.05565784900828677
    },
    {
        "timestamp": "2025-08-06T23:59:03.628235",
        "profit_percentage": -0.06402839692713642
    },
    {
        "timestamp": "2025-08-06T23:59:06.609345",
        "profit_percentage": -0.06402839692713642
    },
    {
        "timestamp": "2025-08-06T23:59:09.570569",
        "profit_percentage": -0.08914004068366924
    },
    {
        "timestamp": "2025-08-06T23:59:12.535416",
        "profit_percentage": 0.007206015207682593
    },
    {
        "timestamp": "2025-08-06T23:59:15.495102",
        "profit_percentage": -0.009551224406110429
    },
    {
        "timestamp": "2025-08-06T23:59:18.445013",
        "profit_percentage": -0.043065703633744915
    },
    {
        "timestamp": "2025-08-06T23:59:21.415512",
        "profit_percentage": -0.026308464019935748
    },
    {
        "timestamp": "2025-08-06T23:59:24.365646",
        "profit_percentage": -0.08076949276481958
    },
    {
        "timestamp": "2025-08-06T23:59:27.416313",
        "profit_percentage": -0.08076949276481958
    },
    {
        "timestamp": "2025-08-06T23:59:30.368185",
        "profit_percentage": -0.08076949276481958
    },
    {
        "timestamp": "2025-08-06T23:59:33.329943",
        "profit_percentage": -0.08076949276481958
    },
    {
        "timestamp": "2025-08-06T23:59:36.330735",
        "profit_percentage": -0.08914004068366924
    },
    {
        "timestamp": "2025-08-06T23:59:39.949955",
        "profit_percentage": -0.08914004068366924
    },
    {
        "timestamp": "2025-08-06T23:59:42.914949",
        "profit_percentage": 0.007325496790823071
    },
    {
        "timestamp": "2025-08-06T23:59:45.874748",
        "profit_percentage": -0.011913121337107797
    },
    {
        "timestamp": "2025-08-06T23:59:48.852399",
        "profit_percentage": -0.011913121337107797
    },
    {
        "timestamp": "2025-08-06T23:59:51.806865",
        "profit_percentage": -0.017443164188386946
    },
    {
        "timestamp": "2025-08-06T23:59:54.766620",
        "profit_percentage": -0.02445921298774452
    },
    {
        "timestamp": "2025-08-06T23:59:57.739556",
        "profit_percentage": -0.01739527192606131
    },
    {
        "timestamp": "2025-08-07T00:00:00.730791",
        "profit_percentage": -0.010342672321638314
    },
    {
        "timestamp": "2025-08-07T00:00:03.748095",
        "profit_percentage": -0.010247067900046794
    },
    {
        "timestamp": "2025-08-07T00:00:07.019396",
        "profit_percentage": -0.005339461700466911
    },
    {
        "timestamp": "2025-08-07T00:00:10.163194",
        "profit_percentage": -0.00506998103512886
    },
    {
        "timestamp": "2025-08-07T00:00:13.384301",
        "profit_percentage": 0.0033132290603693996
    },
    {
        "timestamp": "2025-08-07T00:00:16.421893",
        "profit_percentage": 0.0033132290603693996
    },
    {
        "timestamp": "2025-08-07T00:00:19.820984",
        "profit_percentage": -0.08465394277014195
    },
    {
        "timestamp": "2025-08-07T00:00:22.869674",
        "profit_percentage": -0.08025718558924473
    },
    {
        "timestamp": "2025-08-07T00:00:26.058025",
        "profit_percentage": -0.08025718558924473
    },
    {
        "timestamp": "2025-08-07T00:00:29.605562",
        "profit_percentage": -0.059311658112096405
    },
    {
        "timestamp": "2025-08-07T00:00:33.115049",
        "profit_percentage": -0.03495014015689241
    },
    {
        "timestamp": "2025-08-07T00:00:36.402648",
        "profit_percentage": -0.03495014015689241
    },
    {
        "timestamp": "2025-08-07T00:00:39.378205",
        "profit_percentage": -0.06426330116480598
    },
    {
        "timestamp": "2025-08-07T00:00:42.359988",
        "profit_percentage": -0.05588926591268972
    },
    {
        "timestamp": "2025-08-07T00:00:45.340696",
        "profit_percentage": -0.039141195408441055
    },
    {
        "timestamp": "2025-08-07T00:00:48.315425",
        "profit_percentage": -0.03591112340400377
    },
    {
        "timestamp": "2025-08-07T00:00:51.287125",
        "profit_percentage": -0.044284727766258865
    },
    {
        "timestamp": "2025-08-07T00:00:54.238330",
        "profit_percentage": -0.04601360034782428
    },
    {
        "timestamp": "2025-08-07T00:00:57.185249",
        "profit_percentage": -0.06295216075351752
    },
    {
        "timestamp": "2025-08-07T00:01:00.137803",
        "profit_percentage": -0.07113397893531663
    },
    {
        "timestamp": "2025-08-07T00:01:03.086540",
        "profit_percentage": -0.07113397893531663
    },
    {
        "timestamp": "2025-08-07T00:01:06.060030",
        "profit_percentage": -0.07113397893531663
    },
    {
        "timestamp": "2025-08-07T00:01:09.012042",
        "profit_percentage": -0.07113397893531663
    },
    {
        "timestamp": "2025-08-07T00:01:12.008936",
        "profit_percentage": -0.07113397893531663
    },
    {
        "timestamp": "2025-08-07T00:01:15.010602",
        "profit_percentage": -0.07113397893531663
    },
    {
        "timestamp": "2025-08-07T00:01:17.984154",
        "profit_percentage": -0.07113397893531663
    },
    {
        "timestamp": "2025-08-07T00:01:20.950770",
        "profit_percentage": -0.07113397893531663
    },
    {
        "timestamp": "2025-08-07T00:01:23.909647",
        "profit_percentage": -0.07113397893531663
    }
]